easy-table/EasyTable.py
easy-table/__init__.py
easy_table/EasyTable.py
easy_table/__init__.py
easy_table-0.0.4.dist-info/METADATA
easy_table-0.0.4.dist-info/WHEEL
easy_table-0.0.4.dist-info/top_level.txt
easy_table-0.0.4.dist-info/RECORD
